Metadata-Version: 1.0
Name: row-matchers
Version: 0.1
Summary: Dataset-matching function(s); simple ways for cancelling out confounding factors in datasets
Home-page: http://github.com/EFraim/row_matchers
Author: Evgeny Fraimovitch
Author-email: evgeny@e5fraim6.com
License: MIT
Platform: UNKNOWN
